<?xml version="1.0" standalone="yes"?>
<DistRoot>
  <Dist_Map>
    <Div_Cd>D003</Div_Cd>
    <Dist_Cd>101</Dist_Cd>
    <Blk_Cd>0810105</Blk_Cd>
    <Gp_Cd>0810105090</Gp_Cd>
    <Vlg_Cd>069203</Vlg_Cd>
    <areaName>N/A</areaName>
    <khasraNo>43</khasraNo>
    <FOREST_DIVCODE>DIV015</FOREST_DIVCODE>
    <Tehsil_Cd>00475</Tehsil_Cd>
  </Dist_Map>
  <Dist_Map>
    <Div_Cd>D003</Div_Cd>
    <Dist_Cd>101</Dist_Cd>
    <Blk_Cd>0810105</Blk_Cd>
    <Gp_Cd>0810105440</Gp_Cd>
    <Vlg_Cd>069267</Vlg_Cd>
    <areaName>APASAR-</areaName>
    <khasraNo>67</khasraNo>
    <FOREST_DIVCODE>DIV015</FOREST_DIVCODE>
    <Tehsil_Cd>00475</Tehsil_Cd>
  </Dist_Map>
</DistRoot>